[
    {
        "place_id": "ChIJO6aUY8Gl_DERkG-anItTh3Q",
        "name": "Air Terjun Riam Ampang",
        "link": "https://www.google.com/maps/place/Air+Terjun+Riam+Ampang/data=!4m7!3m6!1s0x31fca5c16394a63b:0x7487538b9c9a6f90!8m2!3d1.055222!4d109.7848085!16s%2Fg%2F11cnsnqs96!19sChIJO6aUY8Gl_DERkG-anItTh3Q?authuser=0&hl=id&rclk=1",
        "main_category": "Tujuan Wisata",
        "categories": [
            "Tujuan Wisata"
        ],
        "rating": 4.6,
        "reviews": 153,
        "address": "3Q4M+3WM Air Terjun Riam Ampang, Pisak, Kec. Tujuh Belas, Kabupaten Bengkayang, Kalimantan Barat 79251"
    },
    {
        "place_id": "ChIJlar-RTOk_DERZBQKYS6M1fM",
        "name": "Wisata Riam Marum Dawar",
        "link": "https://www.google.com/maps/place/Wisata+Riam+Marum+Dawar/data=!4m7!3m6!1s0x31fca43345feaa95:0xf3d58c2e610a1464!8m2!3d1.0554817!4d109.8076016!16s%2Fg%2F11f3zkppc0!19sChIJlar-RTOk_DERZBQKYS6M1fM?authuser=0&hl=id&rclk=1",
        "main_category": "Tujuan Wisata",
        "categories": [
            "Tujuan Wisata"
        ],
        "rating": 4.8,
        "reviews": 57,
        "address": "Wisata Riam Marum Dawar, Dusun Dawar, Jalan Raya Dawar, Desa Pisak, Kecamatan tujuhbelas, Pisak, Kec. Tujuh Belas, Kabupaten Bengkayang, Kalimantan Barat 79251"
    },
    {
        "place_id": "ChIJHdQYf1un4jERKKB-pOCSmZU",
        "name": "Taman Khatulistiwa",
        "link": "https://www.google.com/maps/place/Taman+Khatulistiwa/data=!4m7!3m6!1s0x31e2a75b7f18d41d:0x959992e0a47ea028!8m2!3d0.0009995!4d109.3222052!16s%2Fm%2F05b623h!19sChIJHdQYf1un4jERKKB-pOCSmZU?authuser=0&hl=id&rclk=1",
        "main_category": "Pusat Rekreasi",
        "categories": [
            "Pusat Rekreasi",
            "Museum",
            "Restoran",
            "Tujuan Wisata"
        ],
        "rating": 4.4,
        "reviews": 8297,
        "address": "Taman Khatulistiwa, Jl. Khatulistiwa No.Kel, Batu Layang, Kec. Pontianak Utara, Kota Pontianak, Kalimantan Barat 78244"
    },
    {
        "place_id": "ChIJG3xrJg5ZHS4Ra2IJGmpRVCo",
        "name": "Rumah Radakng, Pontianak Kalimantan Barat",
        "link": "https://www.google.com/maps/place/Rumah+Radakng,+Pontianak+Kalimantan+Barat/data=!4m7!3m6!1s0x2e1d590e266b7c1b:0x2a54516a1a09626b!8m2!3d-0.046917!4d109.320047!16s%2Fg%2F11c2qrrn5x!19sChIJG3xrJg5ZHS4Ra2IJGmpRVCo?authuser=0&hl=id&rclk=1",
        "main_category": "Tujuan Wisata",
        "categories": [
            "Tujuan Wisata",
            "Pusat kebudayaan"
        ],
        "rating": 4.5,
        "reviews": 6059,
        "address": "X83C+62M Rumah Radakng, Pontianak Kalimantan Barat, Sungai Bangkong, Kec. Pontianak Kota, Kota Pontianak, Kalimantan Barat 78113"
    },
    {
        "place_id": "ChIJzbXzNZRZHS4RA5kLYhz-td0",
        "name": "Taman Digulis Pontianak",
        "link": "https://www.google.com/maps/place/Taman+Digulis+Pontianak/data=!4m7!3m6!1s0x2e1d599435f3b5cd:0xddb5fe1c620b9903!8m2!3d-0.0552528!4d109.3500322!16s%2Fg%2F11dylvbm6l!19sChIJzbXzNZRZHS4RA5kLYhz-td0?authuser=0&hl=id&rclk=1",
        "main_category": "Taman",
        "categories": [
            "Taman",
            "Tujuan Wisata"
        ],
        "rating": 4.6,
        "reviews": 4128,
        "address": "Taman Digulis Pontianak, Jl. Jenderal Ahmad Yani No.114, Bansir Laut, Kec. Pontianak Tenggara, Kota Pontianak, Kalimantan Barat 78112"
    },
    {
        "place_id": "ChIJ46-PO_yh4jERdtyD8JatuGs",
        "name": "Pantai Jungkat & Resort",
        "link": "https://www.google.com/maps/place/Pantai+Jungkat+%26+Resort/data=!4m7!3m6!1s0x31e2a1fc3b8fafe3:0x6bb8ad96f083dc76!8m2!3d0.065429!4d109.1921459!16s%2Fg%2F11b6yzrc9_!19sChIJ46-PO_yh4jERdtyD8JatuGs?authuser=0&hl=id&rclk=1",
        "main_category": "Taman",
        "categories": [
            "Taman",
            "Tujuan Wisata"
        ],
        "rating": 4.2,
        "reviews": 3039,
        "address": "Pantai Jungkat & Resort, Jl. Raya Jungkat, Sei Nipah, Kec. Jongkat, Kab. Mempawah, Kalimantan Barat 78351"
    },
    {
        "place_id": "ChIJ4S6U3KpPHS4Ry_LnulnD8Qo",
        "name": "Hutan Albasia",
        "link": "https://www.google.com/maps/place/Hutan+Albasia/data=!4m7!3m6!1s0x2e1d4faadc942ee1:0xaf1c359bae7f2cb!8m2!3d-0.181995!4d109.4414858!16s%2Fg%2F11hdz6kpgj!19sChIJ4S6U3KpPHS4Ry_LnulnD8Qo?authuser=0&hl=id&rclk=1",
        "main_category": "Tujuan Wisata",
        "categories": [
            "Tujuan Wisata"
        ],
        "rating": 4.1,
        "reviews": 380,
        "address": "Hutan Albasia, Jl. KH. Abdurahman Wahid, Kuala Dua, Kec. Sungai Raya, Kabupaten Kubu Raya, Kalimantan Barat 78391"
    },
    {
        "place_id": "ChIJ-3WARfMl_jERb0fT9zmutDE",
        "name": "Gua Maria Bukit Kelam",
        "link": "https://www.google.com/maps/place/Gua+Maria+Bukit+Kelam/data=!4m7!3m6!1s0x31fe25f3458075fb:0x31b4ae39f7d3476f!8m2!3d0.0862333!4d111.6591717!16s%2Fg%2F11c7v_7b1l!19sChIJ-3WARfMl_jERb0fT9zmutDE?authuser=0&hl=id&rclk=1",
        "main_category": "Tujuan Wisata",
        "categories": [
            "Tujuan Wisata"
        ],
        "rating": 4.3,
        "reviews": 281,
        "address": "3MP5+FMV Gua Maria Bukit Kelam, Merpak, Kec. Kelam Permai, Kabupaten Sintang, Kalimantan Barat 78656"
    },
    {
        "place_id": "ChIJw_lgQdQ14zERH8R18PHh-Ps",
        "name": "Bukit jamur bengkayang",
        "link": "https://www.google.com/maps/place/Bukit+jamur+bengkayang/data=!4m7!3m6!1s0x31e335d44160f9c3:0xfbf8e1f1f075c41f!8m2!3d0.7781171!4d109.4754982!16s%2Fg%2F11b6thg9rh!19sChIJw_lgQdQ14zERH8R18PHh-Ps?authuser=0&hl=id&rclk=1",
        "main_category": "Tujuan Wisata",
        "categories": [
            "Tujuan Wisata"
        ],
        "rating": 4.6,
        "reviews": 255,
        "address": "QFHG+65X Bukit jamur bengkayang, Bhakti Mulya, Kec. Bengkayang, Kabupaten Bengkayang, Kalimantan Barat 79213"
    },
    {
        "place_id": "ChIJ-093kurw_DERxAB6M5aNLc8",
        "name": "Air Terjun Riam Dait",
        "link": "https://www.google.com/maps/place/Air+Terjun+Riam+Dait/data=!4m7!3m6!1s0x31fcf0ea92774ffb:0xcf2d8d96337a00c4!8m2!3d0.7264102!4d110.2104838!16s%2Fg%2F11c1g6m45k!19sChIJ-093kurw_DERxAB6M5aNLc8?authuser=0&hl=id&rclk=1",
        "main_category": "Tujuan Wisata",
        "categories": [
            "Tujuan Wisata"
        ],
        "rating": 4.6,
        "reviews": 238,
        "address": "P6G6+H59 Air Terjun Riam Dait, Engkitip Desa, Sekendal, Kec. Air Besar, Kabupaten Landak, Kalimantan Barat 79367"
    },
    {
        "place_id": "ChIJuagnduth_TERKIbhfwCZN9M",
        "name": "Danau Belibis tayan",
        "link": "https://www.google.com/maps/place/Danau+Belibis+tayan/data=!4m7!3m6!1s0x31fd61eb7627a8b9:0xd33799007fe18628!8m2!3d0.0490965!4d110.0040305!16s%2Fg%2F11fl0x3f4w!19sChIJuagnduth_TERKIbhfwCZN9M?authuser=0&hl=id&rclk=1",
        "main_category": "Tujuan Wisata",
        "categories": [
            "Tujuan Wisata"
        ],
        "rating": 4.3,
        "reviews": 234,
        "address": "22X3+JJJ Danau Belibis tayan, Sejotang, Kec. Tayan Hilir, Kabupaten Sanggau, Kalimantan Barat 78563"
    },
    {
        "place_id": "ChIJoYXXqBAi_jERidEQiTMiudQ",
        "name": "Taman Bunggur Sungai Kapuas",
        "link": "https://www.google.com/maps/place/Taman+Bunggur+Sungai+Kapuas/data=!4m7!3m6!1s0x31fe2210a8d785a1:0xd4b922338910d189!8m2!3d0.0781283!4d111.4923552!16s%2Fg%2F11dfqx4p9z!19sChIJoYXXqBAi_jERidEQiTMiudQ?authuser=0&hl=id&rclk=1",
        "main_category": "Museum",
        "categories": [
            "Museum",
            "Tujuan Wisata"
        ],
        "rating": 3.8,
        "reviews": 91,
        "address": "Taman Bunggur Sungai Kapuas, Jl. Pembangunan No.103, Tj. Puri, Kec. Sintang, Kabupaten Sintang, Kalimantan Barat 78613"
    },
    {
        "place_id": "ChIJ6XCx3ITs_DERmAf-US9No4E",
        "name": "Air Terjun Terinting",
        "link": "https://www.google.com/maps/place/Air+Terjun+Terinting/data=!4m7!3m6!1s0x31fcec84dcb170e9:0x81a34d2f51fe0798!8m2!3d0.8232795!4d110.0526194!16s%2Fg%2F11c4wwwxtl!19sChIJ6XCx3ITs_DERmAf-US9No4E?authuser=0&hl=id&rclk=1",
        "main_category": "Tujuan Wisata",
        "categories": [
            "Tujuan Wisata"
        ],
        "rating": 4.5,
        "reviews": 68,
        "address": "R3F3+829 Air Terjun Terinting, Sempatung Lawek, Kec. Air Besar, Kabupaten Landak, Kalimantan Barat 79365"
    },
    {
        "place_id": "ChIJkUh-ADHr_DERlLcxMICT8ms",
        "name": "Air Terjun Bedawat",
        "link": "https://www.google.com/maps/place/Air+Terjun+Bedawat/data=!4m7!3m6!1s0x31fceb31007e4891:0x6bf293803031b794!8m2!3d0.8443975!4d110.0122264!16s%2Fg%2F11crstglgr!19sChIJkUh-ADHr_DERlLcxMICT8ms?authuser=0&hl=id&rclk=1",
        "main_category": "Tujuan Wisata",
        "categories": [
            "Tujuan Wisata"
        ],
        "rating": 4.9,
        "reviews": 55,
        "address": "R2V6+QV5 Air Terjun Bedawat, Sempatung Lawek, Kec. Air Besar, Kabupaten Landak, Kalimantan Barat 79365"
    },
    {
        "place_id": "ChIJmXGO0KeaAS4RrZtpPXlTK24",
        "name": "Bukit Saran",
        "link": "https://www.google.com/maps/place/Bukit+Saran/data=!4m7!3m6!1s0x2e019aa7d08e7199:0x6e2b53793d699bad!8m2!3d-0.4211895!4d111.2969461!16s%2Fg%2F11c6dfvkhm!19sChIJmXGO0KeaAS4RrZtpPXlTK24?authuser=0&hl=id&rclk=1",
        "main_category": "Taman Nasional",
        "categories": [
            "Taman Nasional",
            "Tujuan Wisata"
        ],
        "rating": 4.2,
        "reviews": 18,
        "address": "H7HW+GQG Bukit Saran, Temawang Bulai, Kec. Sepauk, Kabupaten Sintang, Kalimantan Barat 78662"
    },
    {
        "place_id": "ChIJ6YeYjd8q_jERt3X-ixJuJ54",
        "name": "Air Terjun Lepung Iring",
        "link": "https://www.google.com/maps/place/Air+Terjun+Lepung+Iring/data=!4m7!3m6!1s0x31fe2adf8d9887e9:0x9e276e128bfe75b7!8m2!3d0.034167!4d111.834722!16s%2Fg%2F11c327tqyf!19sChIJ6YeYjd8q_jERt3X-ixJuJ54?authuser=0&hl=id&rclk=1",
        "main_category": "Tujuan Wisata",
        "categories": [
            "Tujuan Wisata"
        ],
        "rating": 4.6,
        "reviews": 17,
        "address": "2RMM+MV9 Air Terjun Lepung Iring, Desa, Umin Jaya, Kec. Dedai, Kabupaten Sintang, Kalimantan Barat 78691"
    },
    {
        "place_id": "ChIJIyxkXaSZ_zERnD3Bzezr3fg",
        "name": "Bukit Ampan Kapuas Hulu",
        "link": "https://www.google.com/maps/place/Bukit+Ampan+Kapuas+Hulu/data=!4m7!3m6!1s0x31ff99a45d642c23:0xf8ddebeccdc13d9c!8m2!3d0.4684178!4d112.2850578!16s%2Fg%2F11g0hyvgk4!19sChIJIyxkXaSZ_zERnD3Bzezr3fg?authuser=0&hl=id&rclk=1",
        "main_category": "Tujuan Wisata",
        "categories": [
            "Tujuan Wisata"
        ],
        "rating": 4.9,
        "reviews": 16,
        "address": "F79P+927 Bukit Ampan Kapuas Hulu, nanga pedian, Kec. Pengkadan, Kabupaten Kapuas Hulu, Kalimantan Barat 78759"
    },
    {
        "place_id": "ChIJTXfgDH5H_zERjUT-yy06Xw8",
        "name": "Bukit Babi",
        "link": "https://www.google.com/maps/place/Bukit+Babi/data=!4m7!3m6!1s0x31ff477e0ce0774d:0xf5f3a2dcbfe448d!8m2!3d0.9705837!4d112.2698695!16s%2Fg%2F11szxhvbk2!19sChIJTXfgDH5H_zERjUT-yy06Xw8?authuser=0&hl=id&rclk=1",
        "main_category": "Tujuan Wisata",
        "categories": [
            "Tujuan Wisata"
        ],
        "rating": 4.8,
        "reviews": 8,
        "address": "X7C9+6W Bukit Babi, Lanjak Deras, Batang Lupar, Kapuas Hulu Regency, West Kalimantan 78766"
    },
    {
        "place_id": "ChIJiwO0oSNFAC4Ra973NvS_7So",
        "name": "Wisata alam belaban",
        "link": "https://www.google.com/maps/place/Wisata+alam+belaban/data=!4m7!3m6!1s0x2e004523a1b4038b:0x2aedbff436f7de6b!8m2!3d-0.60389!4d112.2421501!16s%2Fg%2F11spnv0gcs!19sChIJiwO0oSNFAC4Ra973NvS_7So?authuser=0&hl=id&rclk=1",
        "main_category": "Tujuan Wisata",
        "categories": [
            "Tujuan Wisata"
        ],
        "rating": 4.9,
        "reviews": 8,
        "address": "96WR+CVR Wisata alam belaban, Belaban Ella, Kec. Menukung, Kabupaten Melawi, Kalimantan Barat 79682"
    },
    {
        "place_id": "ChIJ-5LqcuvNATIRbay9MCkgQr0",
        "name": "Lubuk Semah",
        "link": "https://www.google.com/maps/place/Lubuk+Semah/data=!4m7!3m6!1s0x3201cdeb72ea92fb:0xbd42202930bdac6d!8m2!3d0.5699657!4d112.857231!16s%2Fg%2F11s4d_8kzd!19sChIJ-5LqcuvNATIRbay9MCkgQr0?authuser=0&hl=id&rclk=1",
        "main_category": "Tujuan Wisata",
        "categories": [
            "Tujuan Wisata"
        ],
        "rating": 4.3,
        "reviews": 7,
        "address": "HV94+XVQ Lubuk Semah, Jl. Lintas Selatan, Tekalong, Mentebah, Kapuas Hulu Regency, West Kalimantan"
    }
]